[
  {
    "family": "id",
    "num_cases": 180,
    "model_rollout_seconds": 0.38176555255324474,
    "one_step_mae": 0.0018954322618406473,
    "one_step_relative_rmse": 0.12667475872569614,
    "one_step_rmse": 0.008049652727398401,
    "rollout_mae": 0.026515441615548398,
    "rollout_relative_rmse": 1.07464390165276,
    "rollout_rmse": 0.06667568694489698,
    "rollout_steps": 199.0,
    "solver_seconds": 0.02799294877331704,
    "model_steps_per_second": 521.2623262342286,
    "solver_steps_per_second": 7108.93309638345
  },
  {
    "family": "parameter_shift",
    "num_cases": 552,
    "model_rollout_seconds": 0.3005029673644247,
    "one_step_mae": 0.0019190514644108496,
    "one_step_relative_rmse": 0.1275525928299496,
    "one_step_rmse": 0.008610398718662074,
    "rollout_mae": 0.02677296691884597,
    "rollout_relative_rmse": 1.052331368452397,
    "rollout_rmse": 0.06947084614480643,
    "rollout_steps": 199.0,
    "solver_seconds": 0.02419384681633201,
    "model_steps_per_second": 662.2230780126359,
    "solver_steps_per_second": 8225.231874480805
  },
  {
    "family": "geometry_shift",
    "num_cases": 416,
    "model_rollout_seconds": 0.28776937176119716,
    "one_step_mae": 0.0019569787550258646,
    "one_step_relative_rmse": 0.12985386428996348,
    "one_step_rmse": 0.00813626798480982,
    "rollout_mae": 0.027142642699450683,
    "rollout_relative_rmse": 1.073912497323293,
    "rollout_rmse": 0.0657619234340158,
    "rollout_steps": 199.0,
    "solver_seconds": 0.02342612096309984,
    "model_steps_per_second": 691.5259910465328,
    "solver_steps_per_second": 8494.790935019038
  },
  {
    "family": "long_rollout",
    "num_cases": 180,
    "long_rollout_rmse": 0.06667568694489698,
    "long_vs_short_ratio": 1.1896606045463103,
    "model_rollout_seconds": 0.2837910927211245,
    "one_step_mae": 0.0018954322618406473,
    "one_step_relative_rmse": 0.12667475872569614,
    "one_step_rmse": 0.008049652727398401,
    "rollout_mae": 0.026515441615548398,
    "rollout_relative_rmse": 1.07464390165276,
    "rollout_rmse": 0.06667568694489698,
    "rollout_steps": 199.0,
    "short_rollout_rmse": 0.08511196398176253,
    "solver_seconds": 0.023482751114190452,
    "model_steps_per_second": 701.2200351036144,
    "solver_steps_per_second": 8474.30520522554
  }
]